jaf/__init__.py
jaf/cli.py
jaf/exceptions.py
jaf/a2a/__init__.py
jaf/a2a/agent.py
jaf/a2a/agent_card.py
jaf/a2a/client.py
jaf/a2a/protocol.py
jaf/a2a/server.py
jaf/a2a/standalone_client.py
jaf/a2a/types.py
jaf/a2a/examples/__init__.py
jaf/a2a/examples/client_example.py
jaf/a2a/examples/integration_example.py
jaf/a2a/examples/server_example.py
jaf/a2a/examples/rag_demo/__init__.py
jaf/a2a/examples/server_demo/__init__.py
jaf/a2a/memory/__init__.py
jaf/a2a/memory/cleanup.py
jaf/a2a/memory/factory.py
jaf/a2a/memory/serialization.py
jaf/a2a/memory/types.py
jaf/a2a/memory/providers/__init__.py
jaf/a2a/memory/providers/composite.py
jaf/a2a/memory/providers/in_memory.py
jaf/a2a/memory/providers/postgres.py
jaf/a2a/memory/providers/redis.py
jaf/a2a/memory/tests/__init__.py
jaf/a2a/memory/tests/run_comprehensive_tests.py
jaf/a2a/memory/tests/test_cleanup.py
jaf/a2a/memory/tests/test_serialization.py
jaf/a2a/memory/tests/test_stress_concurrency.py
jaf/a2a/memory/tests/test_task_lifecycle.py
jaf/a2a/tests/__init__.py
jaf/a2a/tests/run_tests.py
jaf/a2a/tests/test_agent.py
jaf/a2a/tests/test_client.py
jaf/a2a/tests/test_integration.py
jaf/a2a/tests/test_protocol.py
jaf/a2a/tests/test_types.py
jaf/core/__init__.py
jaf/core/agent_tool.py
jaf/core/analytics.py
jaf/core/checkpoint.py
jaf/core/composition.py
jaf/core/engine.py
jaf/core/errors.py
jaf/core/guardrails.py
jaf/core/handoff.py
jaf/core/parallel_agents.py
jaf/core/performance.py
jaf/core/proxy.py
jaf/core/proxy_helpers.py
jaf/core/regeneration.py
jaf/core/state.py
jaf/core/streaming.py
jaf/core/tool_results.py
jaf/core/tools.py
jaf/core/tracing.py
jaf/core/types.py
jaf/core/workflows.py
jaf/memory/__init__.py
jaf/memory/approval_storage.py
jaf/memory/factory.py
jaf/memory/types.py
jaf/memory/utils.py
jaf/memory/providers/__init__.py
jaf/memory/providers/in_memory.py
jaf/memory/providers/postgres.py
jaf/memory/providers/redis.py
jaf/plugins/__init__.py
jaf/plugins/base.py
jaf/policies/__init__.py
jaf/policies/handoff.py
jaf_py-2.6.8.dist-info/licenses/LICENSE
jaf_py-2.6.8.dist-info/METADATA
jaf_py-2.6.8.dist-info/WHEEL
jaf_py-2.6.8.dist-info/entry_points.txt
jaf_py-2.6.8.dist-info/top_level.txt
jaf_py-2.6.8.dist-info/RECORD
