Metadata-Version: 2.4
Name: jaf-py
Version: 2.6.8
Summary: A purely functional agent framework with immutable state and composable tools - Python implementation
Author: JAF Contributors
Maintainer: JAF Contributors
License-Expression: MIT
Project-URL: Homepage, https://github.com/xynehq/jaf-py
Project-URL: Repository, https://github.com/xynehq/jaf-py
Project-URL: Documentation, https://xynehq.github.io/jaf-py/
Project-URL: Issues, https://github.com/xynehq/jaf-py/issues
Project-URL: Changelog, https://github.com/xynehq/jaf-py/releases
Keywords: ai,agents,functional,python,llm,mcp,model-context-protocol,agent-framework,functional-programming
Classifier: Development Status :: 4 - Beta
Classifier: Intended Audience :: Developers
Classifier: Operating System :: OS Independent
Classifier: Programming Language :: Python :: 3
Classifier: Programming Language :: Python :: 3.10
Classifier: Programming Language :: Python :: 3.11
Classifier: Programming Language :: Python :: 3.12
Classifier: Programming Language :: Python :: 3.13
Classifier: Topic :: Software Development :: Libraries :: Python Modules
Classifier: Topic :: Scientific/Engineering :: Artificial Intelligence
Classifier: Topic :: Software Development :: Libraries :: Application Frameworks
Classifier: Typing :: Typed
Requires-Python: >=3.10
License-File: LICENSE
Requires-Dist: pydantic>=2.0.0
Requires-Dist: fastapi>=0.104.0
Requires-Dist: uvicorn[standard]>=0.35.0
Requires-Dist: openai>=1.0.0
Requires-Dist: typing-extensions>=4.5.0
Requires-Dist: websockets>=15.0.0
Requires-Dist: httpx>=0.25.0
Requires-Dist: httpx-sse>=0.4.0
Requires-Dist: google-generativeai>=0.3.0
Requires-Dist: google-auth>=2.20.0
Requires-Dist: python-dotenv>=1.0.0
Requires-Dist: psutil>=5.9.0
Requires-Dist: fastmcp>=0.1.0
Requires-Dist: opentelemetry-api>=1.22.0
Requires-Dist: opentelemetry-sdk>=1.22.0
Requires-Dist: opentelemetry-exporter-otlp>=1.22.0
Requires-Dist: langfuse<3.0.0
Requires-Dist: litellm>=1.76.3
Provides-Extra: tracing
Requires-Dist: opentelemetry-api>=1.22.0; extra == "tracing"
Requires-Dist: opentelemetry-sdk>=1.22.0; extra == "tracing"
Requires-Dist: opentelemetry-exporter-otlp>=1.22.0; extra == "tracing"
Requires-Dist: langfuse<3.0.0; extra == "tracing"
Provides-Extra: attachments
Requires-Dist: PyPDF2>=3.0.0; extra == "attachments"
Requires-Dist: python-docx>=1.1.0; extra == "attachments"
Requires-Dist: openpyxl>=3.1.0; extra == "attachments"
Requires-Dist: pillow>=11.0.0; extra == "attachments"
Requires-Dist: python-magic>=0.4.27; sys_platform != "win32" and extra == "attachments"
Requires-Dist: python-magic-bin>=0.4.14; sys_platform == "win32" and extra == "attachments"
Requires-Dist: aiofiles>=23.0.0; extra == "attachments"
Provides-Extra: dev
Requires-Dist: pytest>=7.0.0; extra == "dev"
Requires-Dist: pytest-asyncio>=0.21.0; extra == "dev"
Requires-Dist: pytest-cov>=4.0.0; extra == "dev"
Requires-Dist: respx>=0.20.0; extra == "dev"
Requires-Dist: black>=23.0.0; extra == "dev"
Requires-Dist: isort>=5.12.0; extra == "dev"
Requires-Dist: mypy>=1.5.0; extra == "dev"
Requires-Dist: ruff>=0.1.0; extra == "dev"
Requires-Dist: hypothesis>=6.0.0; extra == "dev"
Provides-Extra: server
Requires-Dist: uvicorn[standard]>=0.35.0; extra == "server"
Provides-Extra: memory
Requires-Dist: redis>=5.0.0; extra == "memory"
Requires-Dist: psycopg2-binary>=2.9.0; extra == "memory"
Provides-Extra: visualization
Requires-Dist: graphviz>=0.20.0; extra == "visualization"
Provides-Extra: all
Requires-Dist: jaf-py[attachments,dev,memory,server,tracing,visualization]; extra == "all"
Dynamic: license-file
